odoo/addons/project_forecast_line_holidays_public/README.rst
odoo/addons/project_forecast_line_holidays_public/__init__.py
odoo/addons/project_forecast_line_holidays_public/__manifest__.py
odoo/addons/project_forecast_line_holidays_public/i18n/es.po
odoo/addons/project_forecast_line_holidays_public/i18n/fr.po
odoo/addons/project_forecast_line_holidays_public/i18n/it.po
odoo/addons/project_forecast_line_holidays_public/i18n/project_forecast_line_holidays_public.pot
odoo/addons/project_forecast_line_holidays_public/models/__init__.py
odoo/addons/project_forecast_line_holidays_public/models/forecast_line.py
odoo/addons/project_forecast_line_holidays_public/models/hr_holidays_public.py
odoo/addons/project_forecast_line_holidays_public/models/res_company.py
odoo/addons/project_forecast_line_holidays_public/models/res_config_settings.py
odoo/addons/project_forecast_line_holidays_public/readme/CONTRIBUTORS.rst
odoo/addons/project_forecast_line_holidays_public/readme/DESCRIPTION.rst
odoo/addons/project_forecast_line_holidays_public/static/description/icon.png
odoo/addons/project_forecast_line_holidays_public/static/description/index.html
odoo/addons/project_forecast_line_holidays_public/tests/__init__.py
odoo/addons/project_forecast_line_holidays_public/tests/test_forecast_line.py
odoo/addons/project_forecast_line_holidays_public/views/res_config_settings_views.xml
odoo_addon_project_forecast_line_holidays_public-15.0.1.1.1.1.dist-info/METADATA
odoo_addon_project_forecast_line_holidays_public-15.0.1.1.1.1.dist-info/WHEEL
odoo_addon_project_forecast_line_holidays_public-15.0.1.1.1.1.dist-info/top_level.txt
odoo_addon_project_forecast_line_holidays_public-15.0.1.1.1.1.dist-info/RECORD
