Metadata-Version: 2.1
Name: odoo-addon-project_forecast_line_holidays_public
Version: 15.0.1.1.1.1
Summary: Project Forecast Lines taking public holidays into account
Home-page: https://github.com/OCA/project
Author: Camptocamp, Odoo Community Association (OCA)
Author-email: support@odoo-community.org
License: AGPL-3
Classifier: Programming Language :: Python
Classifier: Framework :: Odoo
Classifier: Framework :: Odoo :: 15.0
Classifier: License :: OSI Approved :: GNU Affero General Public License v3
Classifier: Development Status :: 3 - Alpha
Requires-Python: >=3.8
Requires-Dist: odoo-addon-hr-holidays-public<15.1dev,>=15.0dev
Requires-Dist: odoo-addon-project-forecast-line<15.1dev,>=15.0dev
Requires-Dist: odoo<15.1dev,>=15.0a
